rat_king_parser/__init__.py
rat_king_parser/_version.py
rat_king_parser/rkp.py
rat_king_parser/config_parser/__init__.py
rat_king_parser/config_parser/config_parser_exception.py
rat_king_parser/config_parser/rat_config_parser.py
rat_king_parser/config_parser/utils/__init__.py
rat_king_parser/config_parser/utils/config_item.py
rat_king_parser/config_parser/utils/config_normalization.py
rat_king_parser/config_parser/utils/data_utils.py
rat_king_parser/config_parser/utils/dotnet_constants.py
rat_king_parser/config_parser/utils/dotnetpe_payload.py
rat_king_parser/config_parser/utils/decryptors/__init__.py
rat_king_parser/config_parser/utils/decryptors/config_decryptor.py
rat_king_parser/config_parser/utils/decryptors/config_decryptor_aes_with_iv.py
rat_king_parser/config_parser/utils/decryptors/config_decryptor_aes_with_iv_pbkdf.py
rat_king_parser/config_parser/utils/decryptors/config_decryptor_decrypt_xor.py
rat_king_parser/config_parser/utils/decryptors/config_decryptor_ecb.py
rat_king_parser/config_parser/utils/decryptors/config_decryptor_plaintext.py
rat_king_parser/config_parser/utils/decryptors/config_decryptor_random_hardcoded.py
rat_king_parser/config_parser/utils/decryptors/config_decryptor_rijndael.py
rat_king_parser/extern/__init__.py
rat_king_parser/extern/maco/__init__.py
rat_king_parser/extern/maco/rkp_maco.py
rat_king_parser/yara_utils/__init__.py
rat_king_parser/yara_utils/recompile.py
rat_king_parser/yara_utils/rules.yar
rat_king_parser/yara_utils/rules.yarc
rat_king_parser-4.2.1.dist-info/licenses/LICENSE
rat_king_parser-4.2.1.dist-info/METADATA
rat_king_parser-4.2.1.dist-info/WHEEL
rat_king_parser-4.2.1.dist-info/entry_points.txt
rat_king_parser-4.2.1.dist-info/top_level.txt
rat_king_parser-4.2.1.dist-info/RECORD
