Metadata-Version: 2.4
Name: rat-king-parser
Version: 4.2.1
Summary: A robust, multiprocessing-capable, multi-family RAT config parser/config extractor for AsyncRAT, DcRAT, VenomRAT, QuasarRAT, XWorm, Xeno RAT, and cloned/derivative RAT families.
Author-email: jeFF0Falltrades <8444166+jeFF0Falltrades@users.noreply.github.com>
Maintainer-email: jeFF0Falltrades <8444166+jeFF0Falltrades@users.noreply.github.com>
License: Copyright (c) 2024 Jeff Archer
Project-URL: Bug Reports, https://github.com/jeFF0Falltrades/rat_king_parser/issues
Project-URL: Homepage, https://github.com/jeFF0Falltrades/rat_king_parser
Project-URL: Say Thanks!, https://www.buymeacoffee.com/jeff0falltrades
Keywords: asyncrat,dcrat,malware,parser,quasarrat,venomrat,xenorat,xworm
Classifier: Development Status :: 5 - Production/Stable
Classifier: License :: OSI Approved :: MIT License
Classifier: Programming Language :: Python :: 3 :: Only
Classifier: Programming Language :: Python :: 3.10
Classifier: Programming Language :: Python :: 3.11
Classifier: Programming Language :: Python :: 3.12
Classifier: Programming Language :: Python :: 3.13
Requires-Python: >=3.10
License-File: LICENSE
Requires-Dist: dnfile
Requires-Dist: pycryptodomex
Requires-Dist: yara-python
Provides-Extra: dev
Requires-Dist: pre-commit; extra == "dev"
Provides-Extra: maco
Requires-Dist: maco; extra == "maco"
Requires-Dist: validators; extra == "maco"
Dynamic: license-file
